dbt/adapters/presto/__init__.py
dbt/adapters/presto/__version__.py
dbt/adapters/presto/column.py
dbt/adapters/presto/connections.py
dbt/adapters/presto/impl.py
dbt/include/presto/__init__.py
dbt/include/presto/dbt_project.yml
dbt/include/presto/sample_profiles.yml
dbt/include/presto/macros/adapters.sql
dbt/include/presto/macros/catalog.sql
dbt/include/presto/macros/materializations/incremental.sql
dbt/include/presto/macros/materializations/snapshot.sql
dbt/include/presto/macros/materializations/table.sql
dbt/include/presto/macros/materializations/view.sql
dbt_presto-0.21.1.dist-info/METADATA
dbt_presto-0.21.1.dist-info/WHEEL
dbt_presto-0.21.1.dist-info/top_level.txt
dbt_presto-0.21.1.dist-info/RECORD
