Metadata-Version: 2.1
Name: dbt-presto
Version: 0.21.1
Summary: The presto adpter plugin for dbt (data build tool)
Home-page: https://github.com/fishtown-analytics/dbt
Author: Fishtown Analytics
Author-email: info@fishtownanalytics.com
License: UNKNOWN
Platform: UNKNOWN
Requires-Dist: dbt-core (==0.21.1)
Requires-Dist: presto-python-client (==0.7.0)
